yve_help.py
mapper/__init__.py
mapper/domain.py
mapper/exceptions.py
mapper/infrastructure.py
mapper/mappers.py
mapper/transformer.py
yve-0.0.21.dist-info/METADATA
yve-0.0.21.dist-info/WHEEL
yve-0.0.21.dist-info/top_level.txt
yve-0.0.21.dist-info/RECORD
