Metadata-Version: 2.1
Name: yve
Version: 0.0.21
Summary: Chinese Province, City and Area Recognition Utilities
Home-page: UNKNOWN
Author: Hugh
Author-email: UNKNOWN
License: MIT
Keywords: for study
Platform: UNKNOWN
Classifier: Intended Audience :: Developers
Classifier: License :: OSI Approved :: MIT License
Classifier: Operating System :: OS Independent
Classifier: Natural Language :: Chinese (Simplified)
Classifier: Programming Language :: Python :: 3.6
Classifier: Topic :: Text Processing
Classifier: Topic :: Text Processing :: Indexing
Requires-Dist: pandas (>=0.20.0)
Requires-Dist: jieba (>=0.39)
